Metadata-Version: 2.1
Name: acpic
Version: 1.0.0
Summary: acpid event handler for non-root users
Home-page: https://github.com/psliwka/acpic
Author: Piotr Śliwka
Author-email: contact@psliwka.info
License: WTFPL
Platform: UNKNOWN
Requires-Python: >=3.6
